
<?xml version="1.0" encoding="UTF-8"?>
<gresources>
  <gresource prefix="/com/github/alainm23/planner/stylesheet">
    <file alias="animations.css" compressed="true">stylesheet/animations.css</file>
    <file alias="calendar.css" compressed="true">stylesheet/calendar.css</file>
    <file alias="stylesheet.css" compressed="true">stylesheet/stylesheet.css</file>
    <file alias="variables.css" compressed="true">stylesheet/variables.css</file>
    <file alias="sidebar.css" compressed="true">stylesheet/sidebar.css</file>
  </gresource>
  <gresource prefix="/com/github/alainm23/planner">
    <file alias="index.css" compressed="true">stylesheet/index.css</file>

    <file alias="planner-inbox.svg">resources/next/planner-inbox.svg</file>
    <file alias="planner-today.svg">resources/next/planner-today.svg</file>
    <file alias="planner-scheduled.svg">resources/next/planner-scheduled.svg</file>
    <file alias="planner-sidebar-trash.svg">resources/next/planner-sidebar-trash.svg</file>
    <file alias="planner-pin-tack.svg">resources/next/planner-pin-tack.svg</file>
    <file alias="view-sidebar-start-symbolic.svg">resources/next/view-sidebar-start-symbolic.svg</file>
    <file alias="view-sidebar-end-symbolic.svg">resources/next/view-sidebar-end-symbolic.svg</file>

    <file alias="planner-calendar-light.svg">resources/next/planner-calendar-light.svg</file>
    <file alias="planner-calendar-dark.svg">resources/next/planner-calendar-dark.svg</file>
    <file alias="planner-search-light.svg">resources/next/planner-search-light.svg</file>
    <file alias="planner-search-dark.svg">resources/next/planner-search-dark.svg</file>
    <file alias="planner-plus-light.svg">resources/next/planner-plus-light.svg</file>
    <file alias="planner-plus-dark.svg">resources/next/planner-plus-dark.svg</file>
    <file alias="chevron-right-dark.svg">resources/next/chevron-right-dark.svg</file>
    <file alias="chevron-right-light.svg">resources/next/chevron-right-light.svg</file>
    <file alias="planner-plus-circle-light.svg">resources/next/planner-plus-circle-light.svg</file>
    <file alias="planner-plus-circle-dark.svg">resources/next/planner-plus-circle-dark.svg</file>
    <file alias="planner-refresh-light.svg">resources/next/planner-refresh-light.svg</file>
    <file alias="planner-refresh-dark.svg">resources/next/planner-refresh-dark.svg</file>
    <file alias="planner-edit-light.svg">resources/next/planner-edit-light.svg</file>
    <file alias="planner-edit-dark.svg">resources/next/planner-edit-dark.svg</file>
    <file alias="planner-trash-light.svg">resources/next/planner-trash-light.svg</file>
    <file alias="planner-trash-dark.svg">resources/next/planner-trash-dark.svg</file>
    <file alias="planner-star-light.svg">resources/next/planner-star-light.svg</file>
    <file alias="planner-star-dark.svg">resources/next/planner-star-dark.svg</file>
    <file alias="planner-close-circle-light.svg">resources/next/planner-close-circle-light.svg</file>
    <file alias="planner-close-circle-dark.svg">resources/next/planner-close-circle-dark.svg</file>
    <file alias="planner-check-circle-light.svg">resources/next/planner-check-circle-light.svg</file>
    <file alias="planner-check-circle-dark.svg">resources/next/planner-check-circle-dark.svg</file>
  </gresource>
</gresources>
